setup.py
distributions/Binomialdistribution.py
distributions/Gaussiandistribution.py
distributions/Generaldistribution.py
distributions/__init__.py
distributionsGauss.egg-info/PKG-INFO
distributionsGauss.egg-info/SOURCES.txt
distributionsGauss.egg-info/dependency_links.txt
distributionsGauss.egg-info/not-zip-safe
distributionsGauss.egg-info/top_level.txt